wsrouter/__init__.py
wsrouter/cmd.py
wsrouter/message.py
wsrouter/router.py
wsrouter/static/websocket.js
wsrouter-0.8.3.dist-info/WHEEL
wsrouter-0.8.3.dist-info/LICENSE.txt
wsrouter-0.8.3.dist-info/METADATA
wsrouter-0.8.3.dist-info/RECORD
