Metadata-Version: 2.1
Name: wsrouter
Version: 0.8.3
Summary: Starlette Shared WebSocket Endpoint
Home-page: https://gitlab.com/selcouth/wsrouter
License: MIT
Author: David Morris
Author-email: gypsysoftware@gmail.com
Requires-Python: >=3.10,<4.0
Classifier: Development Status :: 4 - Beta
Classifier: Environment :: Web Environment
Classifier: Intended Audience :: Developers
Classifier: License :: OSI Approved :: MIT License
Classifier: Operating System :: OS Independent
Classifier: Programming Language :: Python :: 3
Classifier: Programming Language :: Python :: 3.10
Classifier: Programming Language :: Python :: 3.11
Classifier: Programming Language :: Python :: 3
Classifier: Programming Language :: Python :: 3 :: Only
Classifier: Programming Language :: Python :: 3.10
Classifier: Topic :: Internet :: WWW/HTTP
Requires-Dist: boltons (>=21.0.0)
Requires-Dist: orjson (>=3.7.1)
Requires-Dist: shortuuid (>=1.0.9)
Requires-Dist: starlette (>=0.20.1)
Project-URL: Documentation, https://selcouth.gitlab.io/wsrouter/
Project-URL: Repository, https://gitlab.com/selcouth/wsrouter
